Metadata-Version: 1.1
Name: munger
Version: 0.0.1
Summary: A Python module that munges all variables in a namespace, as a demonstration of some aspects of the Python language.
Home-page: https://github.com/neuroneuro15/munger
Author: Nicholas Del Grosso and Achilleas Koutsou
Author-email: delgrosso.nick@gmail.com
License: GNU
Keywords: example mungin python tutorial
Platform: UNKNOWN
Classifier: Development Status :: 3 - Alpha
Classifier: Topic :: Utilities
Classifier: License :: OSI Approved :: BSD License
